<?xml version="1.0" encoding="UTF-8"?>
<QEDEQ
    xmlns:xsi="http://www.w3.org/2001/XMLSchema-instance"
    xsi:noNamespaceSchemaLocation="http://www.qedeq.org/0_04_01/xml/qedeq.xsd">
  <HEADER email="mime@qedeq.org">
    <SPECIFICATION name="proof_001" ruleVersion="1.00.00">
      <LOCATIONS>
        <LOCATION value="http://www.qedeq.org/0_04_01/sample" />
      </LOCATIONS>
    </SPECIFICATION>
    <TITLE>
      <LATEX language="en">
        <![CDATA[
          First formal proofs.
        ]]>
      </LATEX>
    </TITLE>
    <ABSTRACT>
      <LATEX language="en">
        <![CDATA[
          Here are the first proofs assembled. This module should be formally correct.
        ]]>
      </LATEX>
    </ABSTRACT>
    <AUTHORS>
      <AUTHOR email="michael@meyling.com">
        <NAME>
          <LATEX language="en">
            <![CDATA[
              Michael Meyling
            ]]>
          </LATEX>
        </NAME>
      </AUTHOR>
    </AUTHORS>
  </HEADER>
  <CHAPTER>
    <TITLE>
      <LATEX language="en">
        <![CDATA[
          First
        ]]>
      </LATEX>
    </TITLE>
    <INTRODUCTION>
      <LATEX language="en">
        <![CDATA[
          After presenting some axioms we show some formal proofs.
        ]]>
      </LATEX>
    </INTRODUCTION>
    
    
    <SECTION>
      <TITLE>
        <LATEX language="en">
          <![CDATA[
            Axioms
          ]]>
        </LATEX>
      </TITLE>
      <INTRODUCTION>
        <LATEX language="en">
          <![CDATA[
            Here we state our axioms.
          ]]>
        </LATEX>
      </INTRODUCTION>
      <SUBSECTIONS>
        <NODE id="axiom:disjunction_idempotence">
          <NAME>
            <LATEX language="en">axiom of disjunction idempotence</LATEX>
          </NAME>
          <TITLE>
            <LATEX language="en">Disjunction Idempotence</LATEX>
          </TITLE>
          <AXIOM>
            <FORMULA>
              <IMPL>
                <OR>
                  <PREDVAR id="A" />
                  <PREDVAR id="A" />
                </OR>
                <PREDVAR id="A" />
              </IMPL>
            </FORMULA>
          </AXIOM>
        </NODE>
        <NODE id="axiom:disjunction_weakening">
          <NAME>
            <LATEX language="en">axiom of weakening</LATEX>
          </NAME>
          <TITLE>
            <LATEX language="en">Axiom of Weakening</LATEX>
          </TITLE>
          <AXIOM>
            <FORMULA>
              <IMPL>
                <PREDVAR id="A" />
                <OR>
                  <PREDVAR id="A" />
                  <PREDVAR id="B" />
                </OR>
              </IMPL>
            </FORMULA>
          </AXIOM>
        </NODE>
        
        <NODE id="axiom:disjunction_commutative">
          <NAME>
            <LATEX language="en">commutativity of the disjunction</LATEX>
          </NAME>
          <TITLE>
            <LATEX language="en">Commutativity of the Disjunction</LATEX>
          </TITLE>
          <AXIOM>
            <FORMULA>
              <IMPL>
                <OR>
                  <PREDVAR id="A" />
                  <PREDVAR id="B" />
                </OR>
                <OR>
                  <PREDVAR id="B" />
                  <PREDVAR id="A" />
                </OR>
              </IMPL>
            </FORMULA>
          </AXIOM>
        </NODE>
        
        <NODE id="axiom:disjunction_addition">
          <NAME>
            <LATEX language="en">axiom of disjunctive addition</LATEX>
          </NAME>
          <TITLE>
            <LATEX language="en">Disjunctive Addition</LATEX>
          </TITLE>
          <AXIOM>
            <FORMULA>
              <IMPL>
                <IMPL>
                  <PREDVAR id="A" />
                  <PREDVAR id="B" />
                </IMPL>
                <IMPL>
                  <IMPL>
                    <PREDVAR id="C" />
                    <PREDVAR id="A" />
                  </IMPL>
                  <OR>
                    <PREDVAR id="C" />
                    <PREDVAR id="B" />
                  </OR>
                </IMPL>
              </IMPL>
            </FORMULA>
          </AXIOM>
        </NODE>
      </SUBSECTIONS>
    </SECTION>
    <SECTION>
      <TITLE>
        <LATEX language="en">
          <![CDATA[
            One
          ]]>
        </LATEX>
      </TITLE>
      <INTRODUCTION>
        <LATEX language="en">
          <![CDATA[
            Here we start.
          ]]>
        </LATEX>
      </INTRODUCTION>
      <SUBSECTIONS>
       <NODE id="proposition:one" level="formal">
          <THEOREM>
            <FORMULA>
              <IMPL>
                <PREDVAR id="A" />
                <PREDVAR id="A" />
              </IMPL>
            </FORMULA>
            <FORMAL_PROOF>
              <LINES>
                <L label="1">
                  <FORMULA>
                    <IMPL>
                      <PREDVAR id="A" />
                      <OR>
                        <PREDVAR id="A" />
                        <PREDVAR id="B" />
                      </OR>
                    </IMPL>
                  </FORMULA>
                  <ADD ref="axiom:disjunction_weakening" />
                </L>
                <L label="2">
                  <FORMULA>
                    <IMPL>
                      <PREDVAR id="A" />
                      <OR>
                        <PREDVAR id="A" />
                        <PREDVAR id="A" />
                      </OR>
                    </IMPL>
                  </FORMULA>
                  <SUBST_PREDVAR ref="1">
                    <PREDVAR id="B" />
                    <FORMULA>
                      <PREDVAR id="A" />
                    </FORMULA>
                  </SUBST_PREDVAR>
                </L>
                <L label="3">
                  <FORMULA>
                    <IMPL>
                      <OR>
                        <PREDVAR id="A" />
                        <PREDVAR id="A" />
                      </OR>
                      <PREDVAR id="A" />
                    </IMPL>
                  </FORMULA>
                  <ADD ref="axiom:disjunction_idempotence" />
                </L>
                <L label="4">
                  <FORMULA>
                    <IMPL>
                      <IMPL>
                        <PREDVAR id="A" />
                        <PREDVAR id="B" />
                      </IMPL>
                      <IMPL>
                        <IMPL>
                          <PREDVAR id="C" />
                          <PREDVAR id="A" />
                        </IMPL>
                        <IMPL>
                          <PREDVAR id="C" />
                          <PREDVAR id="B" />
                        </IMPL>
                      </IMPL>
                    </IMPL>
                  </FORMULA>
                  <ADD ref="axiom:disjunction_addition" />
                </L>
                <L label="5">
                  <FORMULA>
                    <IMPL>
                      <IMPL>
                        <PREDVAR id="D" />
                        <PREDVAR id="B" />
                      </IMPL>
                      <IMPL>
                        <IMPL>
                          <PREDVAR id="C" />
                          <PREDVAR id="D" />
                        </IMPL>
                        <IMPL>
                          <PREDVAR id="C" />
                          <PREDVAR id="B" />
                        </IMPL>
                      </IMPL>
                    </IMPL>
                  </FORMULA>
                  <SUBST_PREDVAR ref="4" >
                    <PREDVAR id="P" />
                    <FORMULA>
                      <PREDVAR id="D" />
                    </FORMULA>
                  </SUBST_PREDVAR>
                </L>
                <L label="6">
                  <FORMULA>
                    <IMPL>
                      <IMPL>
                        <PREDVAR id="D" />
                        <PREDVAR id="A" />
                      </IMPL>
                      <IMPL>
                        <IMPL>
                          <PREDVAR id="C" />
                          <PREDVAR id="D" />
                        </IMPL>
                        <IMPL>
                          <PREDVAR id="C" />
                          <PREDVAR id="A" />
                        </IMPL>
                      </IMPL>
                    </IMPL>
                  </FORMULA>
                  <SUBST_PREDVAR ref="5" >
                    <PREDVAR id="B" />
                    <FORMULA>
                      <PREDVAR id="A" />
                    </FORMULA>
                  </SUBST_PREDVAR>
                </L>
                <L label="7">
                  <FORMULA>
                    <IMPL>
                      <IMPL>
                        <PREDVAR id="D" />
                        <PREDVAR id="A" />
                      </IMPL>
                      <IMPL>
                        <IMPL>
                          <PREDVAR id="A" />
                          <PREDVAR id="D" />
                        </IMPL>
                        <IMPL>
                          <PREDVAR id="A" />
                          <PREDVAR id="A" />
                        </IMPL>
                      </IMPL>
                    </IMPL>
                  </FORMULA>
                  <SUBST_PREDVAR ref="6" >
                    <PREDVAR id="C" />
                    <FORMULA>
                      <PREDVAR id="A" />
                    </FORMULA>
                  </SUBST_PREDVAR>
                </L>
                <L label="8">
                  <FORMULA>
                    <IMPL>
                      <IMPL>
                        <OR>
                          <PREDVAR id="A" />
                          <PREDVAR id="A" />
                        </OR>
                        <PREDVAR id="A" />
                      </IMPL>
                      <IMPL>
                        <IMPL>
                          <PREDVAR id="A" />
                          <OR>
                            <PREDVAR id="A" />
                            <PREDVAR id="A" />
                          </OR>
                        </IMPL>
                        <IMPL>
                          <PREDVAR id="A" />
                          <PREDVAR id="A" />
                        </IMPL>
                      </IMPL>
                    </IMPL>
                  </FORMULA>
                  <SUBST_PREDVAR ref="7" >
                    <PREDVAR id="D" />
                    <FORMULA>
                      <OR>
                        <PREDVAR id="A" />
                        <PREDVAR id="A" />
                      </OR>
                    </FORMULA>
                  </SUBST_PREDVAR>
                </L>
                <L label="9">
                  <FORMULA>
                    <IMPL>
                      <IMPL>
                        <PREDVAR id="A" />
                        <OR>
                          <PREDVAR id="A" />
                          <PREDVAR id="A" />
                        </OR>
                      </IMPL>
                      <IMPL>
                        <PREDVAR id="A" />
                        <PREDVAR id="A" />
                      </IMPL>
                    </IMPL>
                  </FORMULA>
                  <MP ref1="8" ref2="3" />
                </L>
                <L label="10">
                  <FORMULA>
                    <IMPL>
                      <PREDVAR id="A" />
                      <PREDVAR id="A" />
                    </IMPL>
                  </FORMULA>
                  <MP ref1="9" ref2="2" />
                </L>
              </LINES>
            </FORMAL_PROOF>
          </THEOREM>
        </NODE>
      </SUBSECTIONS>
    </SECTION>
  </CHAPTER>
</QEDEQ>
